example/simple/__init__.py
example/simple/processor.py
greble_flow/__init__.py
greble_flow/__main__.py
greble_flow/managment/__init__.py
greble_flow/managment/executor.py
greble_flow/managment/manager.py
greble_flow/managment/processor.py
greble_flow/processors/__init__.py
greble_flow/processors/base.py
greble_flow/web/__init__.py
greble_flow/web/managment.py
greble_flow-0.0.3.5.dist-info/LICENSE
greble_flow-0.0.3.5.dist-info/METADATA
greble_flow-0.0.3.5.dist-info/WHEEL
greble_flow-0.0.3.5.dist-info/top_level.txt
greble_flow-0.0.3.5.dist-info/RECORD
