Metadata-Version: 2.1
Name: greble-flow
Version: 0.0.3.5
Summary: Greble flow
Home-page: https://github.com/greble/python-flow-helper
Author: Greble
Author-email: info@greble.io
License: UNKNOWN
Platform: UNKNOWN
Requires-Dist: greble-flow (>=0.0.1)
Requires-Dist: click
Requires-Dist: flask
